[
	{
		"name": "廖鸿兵",
		"icon_url": "",
		"subject": "男科",
		"department": "暨南大学附属第一医院"
	},
	{
		"name": "李云龙",
		"icon_url": "abc",
		"subject": "妇科",
		"department": "广东省中医院"
	},
	{
		"name": "卢润诗",
		"icon_url": "",
		"subject": "男科",
		"department": "中山大学中山眼科中心"
	},
	{
		"name": "薛耀明",
		"icon_url": "",
		"subject": "儿科",
		"department": "南方医科大学南方医院"
	},
	{
		"name": "李红艳",
		"icon_url": "",
		"subject": "胃病科",
		"department": "广东省教育中心"
	},
	{
		"name": "王树声",
		"icon_url": "",
		"subject": "肾脏科",
		"department": "暨南大学附属第一医院"
	},
	{
		"name": "葛坚",
		"icon_url": "",
		"subject": "肾脏科",
		"department": "中山眼科中心"
	},
	{
		"name": "冯忻",
		"icon_url": "",
		"subject": "肾脏科",
		"department": "南方医科大学中西医结合医院"
	},
	{
		"name": "李永新",
		"icon_url": "",
		"subject": "妇科",
		"department": "北京同仁医院"
	}
]